main.py
piper.py
gascompressibility/__init__.py
gascompressibility/zfactor.py
gascompressibility/pseudocritical/__init__.py
gascompressibility/pseudocritical/piper.py
gascompressibility/pseudocritical/sutton.py
gascompressibility/utilities/__init__.py
gascompressibility/utilities/utilities.py
gascompressibility/z_correlation/DAK.py
gascompressibility/z_correlation/__init__.py
gascompressibility/z_correlation/hall_yarborough.py
gascompressibility/z_correlation/kareem.py
gascompressibility/z_correlation/londono.py
gascompressibility/z_correlation/z_helper.py
tests/__init__.py
tests/test_gascomp.py
gascompressibility-1.0.0.dist-info/LICENSE
gascompressibility-1.0.0.dist-info/METADATA
gascompressibility-1.0.0.dist-info/WHEEL
gascompressibility-1.0.0.dist-info/top_level.txt
gascompressibility-1.0.0.dist-info/RECORD
