Metadata-Version: 2.1
Name: gascompressibility
Version: 1.0.0
Summary: GasCompressibility-py is a Python library for calculating the gas compressibility factor, Z, based on real gas law.
Home-page: https://github.com/aegis4048/GasCompressibiltiy-py/tree/main
Author: Eric Kim
Author-email: aegis4048@gmail.com
License: MIT
Classifier: Development Status :: 5 - Production/Stable
Classifier: Intended Audience :: Science/Research
Classifier: License :: OSI Approved :: MIT License
Classifier: Natural Language :: English
Classifier: Programming Language :: Python :: 3.6
Classifier: Programming Language :: Python :: 3.7
Classifier: Programming Language :: Python :: 3.8
Classifier: Programming Language :: Python :: 3.9
Classifier: Programming Language :: Python :: 3.10
Classifier: Programming Language :: Python :: 3.11
Classifier: Topic :: Scientific/Engineering :: Information Analysis
License-File: LICENSE
Requires-Dist: numpy (>=1.14)
Requires-Dist: scipy (>=1.5)
Requires-Dist: matplotlib (>=3.2.1)
